myst_nb_bokeh-2024.1.0.post1.dist-info/METADATA
myst_nb_bokeh-2024.1.0.post1.dist-info/WHEEL
myst_nb_bokeh-2024.1.0.post1.dist-info/entry_points.txt
myst_nb_bokeh-2024.1.0.post1.dist-info/licenses/AUTHORS.md
myst_nb_bokeh-2024.1.0.post1.dist-info/licenses/LICENSE
myst_nb_bokeh/__init__.py
myst_nb_bokeh/py.typed
myst_nb_bokeh-2024.1.0.post1.dist-info/RECORD
