Metadata-Version: 2.1
Name: myst-nb-bokeh
Version: 2024.1.0.post1
Summary: MyST-NB-Bokeh includes functions for gluing and pasting Bokeh figures in MyST documents.
Keywords: docutils,sphinx,bokeh
Author-Email: Bryan Weber <bryan.w.weber@gmail.com>
License: BSD-3-Clause
Classifier: Development Status :: 5 - Production/Stable
Classifier: Framework :: Sphinx :: Extension
Classifier: Intended Audience :: Developers
Classifier: License :: OSI Approved :: BSD License
Classifier: Programming Language :: Python :: 3
Classifier: Programming Language :: Python :: 3 :: Only
Classifier: Programming Language :: Python :: 3.10
Classifier: Programming Language :: Python :: 3.11
Classifier: Programming Language :: Python :: 3.12
Classifier: Programming Language :: Python :: 3.13
Classifier: Programming Language :: Python :: 3.9
Classifier: Programming Language :: Python :: Implementation :: CPython
Classifier: Topic :: Software Development :: Libraries :: Python Modules
Classifier: Topic :: Text Processing :: Markup
Project-URL: Homepage, https://github.com/bryanwweber/myst-nb-bokeh
Project-URL: Documentation, https://myst-nb-bokeh.readthedocs.io/en/latest/
Project-URL: Source, https://github.com/bryanwweber/myst-nb-bokeh
Project-URL: Tracker, https://github.com/bryanwweber/myst-nb-bokeh/issues
Requires-Python: >=3.10
Requires-Dist: IPython>=8.20.0
Requires-Dist: bokeh>=3.3.4
Requires-Dist: myst-nb>=1.0.0
Requires-Dist: sphinx>=7.2.6
Requires-Dist: sphinx-book-theme>=1.1.0; extra == "docs"
Provides-Extra: docs
